<VerificationJob>
  <Configuration>
    <AnalyzeChecksIndividually value="false" />
    <BitcodeTraces value="false" />
    <DumpVerifierBitcodeFiles value="false" />
    <EnableSlicing value="false" />
    <EntryPoint value="walRewriteChecksums" />
    <FixPoint value="true" />
    <ForkJobs value="true" />
    <Hosted value="true" />
    <IgnoreMissingFunctions value="false" />
    <InitializedGlobals value="false" />
    <LoopUnrollBound value="1" />
    <OverApproxVaArgs value="false" />
    <SourceDirectory value="/home/i12/mbuening/100_Dissertation/SQlite/sqlite/bld" />
    <StopEncodingAfterCheck value="false" />
    <StopEncodingAfterCheckLoop value="0" />
    <TimeOut value="600" />
    <XMLTraces value="false" />
  </Configuration>
  <CheckList>
    <Check id="9708" location="10604" category="implicit.conversion.overflow" status="todo" scope="walRewriteChecksums" />
    <Check id="9709" location="10605" category="arithmetic.overflow" status="todo" scope="walRewriteChecksums" />
    <Check id="9712" location="10608" category="arithmetic.overflow" status="todo" scope="walRewriteChecksums" />
    <Check id="9713" location="10610" category="arithmetic.overflow" status="todo" scope="walRewriteChecksums" />
    <Check id="9715" location="10612" category="arithmetic.overflow" status="todo" scope="walRewriteChecksums" />
    <Check id="9717" location="10614" category="arithmetic.overflow.warning" status="todo" scope="walRewriteChecksums" />
    <Check id="9718" location="10616" category="arithmetic.overflow.warning" status="todo" scope="walRewriteChecksums" />
    <Check id="9722" location="10621" category="arithmetic.overflow" status="todo" scope="walRewriteChecksums" />
    <Check id="9730" location="10628" category="arithmetic.overflow.warning" status="todo" scope="walRewriteChecksums" />
    <Check id="9731" location="10630" category="arithmetic.overflow" status="todo" scope="walRewriteChecksums" />
    <Check id="9733" location="10632" category="arithmetic.overflow" status="todo" scope="walRewriteChecksums" />
    <Check id="9735" location="10634" category="arithmetic.overflow.warning" status="todo" scope="walRewriteChecksums" />
    <Check id="9738" location="10637" category="arithmetic.overflow" status="todo" scope="walRewriteChecksums" />
    <Check id="9739" location="10638" category="arithmetic.overflow" status="todo" scope="walRewriteChecksums" />
  </CheckList>
  <Status>initialized</Status>
</VerificationJob>
