<VerificationJob>
  <Configuration>
    <AnalyzeChecksIndividually value="true" />
    <BitcodeTraces value="false" />
    <CheckCallers value="true" />
    <EnableSlicing value="false" />
    <EntryPoint value="ahrs_main" />
    <FixPoint value="true" />
    <Hosted value="true" />
    <IgnoreMissingFunctions value="true" />
    <InitializedGlobals value="false" />
    <LoopUnrollBound value="1" />
    <PreconditionLocation value="jobs/317" />
    <SourceDirectory value="/home/i12/mbuening/100_Dissertation/MNAV/MNAV1.5" />
    <TimeOut value="300" />
  </Configuration>
  <CheckList>
    <Check id="2313" location="2285" category="arrayindex" status="safe|loopboundreached" scope="snap_time_interval">
      <Annotations>
        <Annotation>An array can be indexed out of bounds.</Annotation>
        <Annotation>A loop bound was reached (/home/i12/mbuening/100_Dissertation/MNAV/MNAV1.5//home/i12/mbuening/100_Dissertation/MNAV/MNAV1.5/matrix.c:71:2)</Annotation>
        <Annotation>A loop bound was reached (/home/i12/mbuening/100_Dissertation/MNAV/MNAV1.5//home/i12/mbuening/100_Dissertation/MNAV/MNAV1.5/matrix.c:71:2)</Annotation>
      </Annotations>
      <EntryStatus>
        <SingleEntryStatus>ahrs_main, safe|loopboundreached</SingleEntryStatus>
        <SingleEntryStatus>navigation, unknown</SingleEntryStatus>
      </EntryStatus>
    </Check>
  </CheckList>
  <Annotation>allunsafe</Annotation>
  <Status>allsafe</Status>
</VerificationJob>
