<VerificationJob>
  <Configuration>
    <AnalyzeChecksIndividually value="true" />
    <BitcodeTraces value="false" />
    <CheckCallers value="true" />
    <DumpVerifierBitcodeFiles value="false" />
    <EnableSlicing value="true" />
    <EntryPoint value="sqlite3_result_error_toobig" />
    <FixPoint value="true" />
    <ForkJobs value="true" />
    <Hosted value="true" />
    <IgnoreMissingFunctions value="false" />
    <InitializedGlobals value="false" />
    <LoopUnrollBound value="1" />
    <PreconditionLocation value="jobs/4267" />
    <SourceDirectory value="/home/i12/mbuening/100_Dissertation/SQlite/sqlite/bld" />
    <TimeOut value="600" />
    <XMLTraces value="false" />
  </Configuration>
  <CheckList>
    <Check id="12874" location="13916" category="implicit.conversion.overflow" status="unsafe|loopboundreached" scope="sqlite3VdbeMemSetStr">
      <Annotations>
        <Annotation>An implicit conversion operation can overflow.</Annotation>
        <Annotation>A loop bound was reached (/home/i12/mbuening/100_Dissertation/SQlite/sqlite/bld//home/i12/mbuening/100_Dissertation/SQlite/sqlite/bld/sqlite3.c:78146:7)</Annotation>
      </Annotations>
      <EntryStatus>
        <SingleEntryStatus>bindText, unknown</SingleEntryStatus>
        <SingleEntryStatus>setResultStrOrError, unknown</SingleEntryStatus>
        <SingleEntryStatus>sqlite3Utf16to8, unknown</SingleEntryStatus>
        <SingleEntryStatus>sqlite3ValueSetStr, unknown</SingleEntryStatus>
        <SingleEntryStatus>sqlite3VdbeExec, unknown</SingleEntryStatus>
        <SingleEntryStatus>sqlite3VdbeExpandSql, unknown</SingleEntryStatus>
        <SingleEntryStatus>sqlite3VdbeList, unknown</SingleEntryStatus>
        <SingleEntryStatus>sqlite3VdbeSetColName, unknown</SingleEntryStatus>
        <SingleEntryStatus>sqlite3_result_error, unknown</SingleEntryStatus>
        <SingleEntryStatus>sqlite3_result_error16, unknown</SingleEntryStatus>
        <SingleEntryStatus>sqlite3_result_error_code, unknown</SingleEntryStatus>
        <SingleEntryStatus>sqlite3_result_error_toobig, unsafe|loopboundreached</SingleEntryStatus>
        <SingleEntryStatus>valueFromExpr, unknown</SingleEntryStatus>
      </EntryStatus>
    </Check>
  </CheckList>
  <Annotation>allunsafe</Annotation>
  <Status>allunsafe</Status>
</VerificationJob>
