<VerificationJob>
  <Configuration>
    <AnalyzeChecksIndividually value="true" />
    <BitcodeTraces value="false" />
    <EnableSlicing value="false" />
    <EntryPoint value="config_int_out_ctrl" />
    <FixPoint value="true" />
    <IgnoreMissingFunctions value="false" />
    <InitializedGlobals value="false" />
    <LoopUnrollBound value="12" />
    <PreconditionLocation value="jobs/443" />
    <SourceDirectory value="/home/i12/mbuening/100_Dissertation/BMI160/BMI160_driver" />
    <TimeOut value="300" />
  </Configuration>
  <CheckList>
    <Check id="1933" location="2026" category="implicit.conversion.overflow" status="safe" scope="config_int_out_ctrl" />
  </CheckList>
  <Annotation>allsafe</Annotation>
  <Status>allsafe</Status>
</VerificationJob>
