<VerificationJob>
  <Configuration>
    <AnalyzeChecksIndividually value="true" />
    <BitcodeTraces value="false" />
    <CheckCallers value="true" />
    <DumpVerifierBitcodeFiles value="false" />
    <EnableSlicing value="true" />
    <EntryPoint value="sqlite3FkActions" />
    <FixPoint value="true" />
    <ForkJobs value="true" />
    <Hosted value="true" />
    <IgnoreMissingFunctions value="false" />
    <InitializedGlobals value="false" />
    <LoopUnrollBound value="1" />
    <SourceDirectory value="/home/i12/mbuening/100_Dissertation/SQlite/sqlite/bld" />
    <TimeOut value="600" />
    <XMLTraces value="false" />
  </Configuration>
  <CheckList>
    <Check id="19809" location="21981" category="implicit.conversion.overflow" status="todo" scope="fkActionTrigger">
      <EntryStatus>
        <SingleEntryStatus>sqlite3FkActions, todo</SingleEntryStatus>
      </EntryStatus>
    </Check>
  </CheckList>
  <Status>initialized</Status>
</VerificationJob>
