<VerificationJob>
  <Configuration>
    <AnalyzeChecksIndividually value="true" />
    <BitcodeTraces value="false" />
    <DumpVerifierBitcodeFiles value="false" />
    <EnableSlicing value="true" />
    <EntryPoint value="sqlite3ParseUri" />
    <FixPoint value="true" />
    <ForkJobs value="true" />
    <Hosted value="true" />
    <IgnoreMissingFunctions value="false" />
    <InitializedGlobals value="false" />
    <LoopUnrollBound value="1" />
    <PreconditionLocation value="jobs/8322" />
    <PreconditionNumber value="5" />
    <SourceDirectory value="/home/i12/mbuening/100_Dissertation/SQlite/sqlite/bld" />
    <StopEncodingAfterCheck value="true" />
    <StopEncodingAfterCheckLoop value="1" />
    <TimeOut value="600" />
    <XMLTraces value="false" />
  </Configuration>
  <CheckList>
    <Check id="27389" location="30675" category="implicit.conversion.overflow" status="safe|loopboundreached" scope="sqlite3ParseUri">
      <Annotations>
        <Annotation>A loop bound was reached (/home/i12/mbuening/100_Dissertation/SQlite/sqlite/bld//home/i12/mbuening/100_Dissertation/SQlite/sqlite/bld/sqlite3.c:168023:7)</Annotation>
      </Annotations>
      <EntryStatus>
        <SingleEntryStatus>sqlite3ParseUri, todo</SingleEntryStatus>
      </EntryStatus>
    </Check>
  </CheckList>
  <Annotation>allsafe</Annotation>
  <Status>allsafe</Status>
</VerificationJob>
