<VerificationJob>
  <Configuration>
    <AnalyzeChecksIndividually value="true" />
    <BitcodeTraces value="false" />
    <DumpVerifierBitcodeFiles value="false" />
    <EnableSlicing value="false" />
    <EntryPoint value="writefileFunc" />
    <FixPoint value="true" />
    <ForkJobs value="true" />
    <HavocLimit value="1" />
    <Hosted value="true" />
    <IgnoreMissingFunctions value="false" />
    <InitializedGlobals value="false" />
    <LoopUnrollBound value="1" />
    <PreconditionLocation value="jobs/116" />
    <SourceDirectory value="/home/i12/mbuening/100_Dissertation/SQlite/sqlite/bld" />
    <TimeOut value="600" />
    <XMLTraces value="false" />
  </Configuration>
  <CheckList>
    <Check id="1184" location="1509" category="explicit.conversion.overflow" status="unsafe|functionbodymissing" scope="writefileFunc">
      <Annotations>
        <Annotation>An explicit conversion operation can overflow.</Annotation>
        <Annotation>The function body for __errno_location is missing (/home/i12/mbuening/100_Dissertation/SQlite/sqlite/bld//home/i12/mbuening/100_Dissertation/SQlite/sqlite/bld/shell.c:2630:17)</Annotation>
      </Annotations>
    </Check>
  </CheckList>
  <Annotation>allunsafe</Annotation>
  <Status>allunsafe</Status>
</VerificationJob>
