<VerificationJob>
  <Configuration>
    <AnalyzeChecksIndividually value="true" />
    <BitcodeTraces value="false" />
    <EnableSlicing value="false" />
    <EntryPoint value="uplink_acq" />
    <FixPoint value="true" />
    <HavocLimit value="1" />
    <Hosted value="true" />
    <IgnoreMissingFunctions value="false" />
    <InitializedGlobals value="false" />
    <LoopUnrollBound value="3" />
    <PreconditionLocation value="jobs/411" />
    <SourceDirectory value="/home/i12/mbuening/100_Dissertation/MNAV/MNAV1.5" />
    <TimeOut value="300" />
  </Configuration>
  <CheckList>
    <Check id="1858" location="1830" category="arrayindex" status="safe|functionbodymissing" scope="uplink_acq">
      <Annotations>
        <Annotation>The function body for printf is missing (/home/i12/mbuening/100_Dissertation/MNAV/MNAV1.5//home/i12/mbuening/100_Dissertation/MNAV/MNAV1.5/uplink.c:58:4)</Annotation>
      </Annotations>
    </Check>
  </CheckList>
  <Annotation>allsafe</Annotation>
  <Status>allsafe</Status>
</VerificationJob>
