<VerificationJob>
  <Configuration>
    <AnalyzeChecksIndividually value="false" />
    <BitcodeTraces value="false" />
    <DumpVerifierBitcodeFiles value="false" />
    <EnableSlicing value="false" />
    <EntryPoint value="quoteFunc" />
    <FixPoint value="true" />
    <ForkJobs value="true" />
    <Hosted value="true" />
    <IgnoreMissingFunctions value="false" />
    <InitializedGlobals value="false" />
    <LoopUnrollBound value="1" />
    <OverApproxVaArgs value="false" />
    <SourceDirectory value="/home/i12/mbuening/100_Dissertation/SQlite/sqlite/bld" />
    <StopEncodingAfterCheck value="false" />
    <StopEncodingAfterCheckLoop value="0" />
    <TimeOut value="600" />
    <XMLTraces value="false" />
  </Configuration>
  <CheckList>
    <Check id="19106" location="21125" category="arithmetic.overflow" status="todo" scope="quoteFunc" />
    <Check id="19107" location="21126" category="arithmetic.overflow" status="todo" scope="quoteFunc" />
    <Check id="19108" location="21127" category="arithmetic.overflow" status="todo" scope="quoteFunc" />
    <Check id="19109" location="21128" category="arrayindex" status="todo" scope="quoteFunc" />
    <Check id="19112" location="21129" category="shift.of.negative" status="todo" scope="quoteFunc" />
    <Check id="19114" location="21131" category="arithmetic.overflow" status="todo" scope="quoteFunc" />
    <Check id="19115" location="21132" category="arithmetic.overflow" status="todo" scope="quoteFunc" />
    <Check id="19116" location="21133" category="arrayindex" status="todo" scope="quoteFunc" />
    <Check id="19118" location="21135" category="arithmetic.overflow" status="todo" scope="quoteFunc" />
    <Check id="19119" location="21136" category="arithmetic.overflow" status="todo" scope="quoteFunc" />
    <Check id="19121" location="21138" category="arithmetic.overflow" status="todo" scope="quoteFunc" />
    <Check id="19122" location="21139" category="arithmetic.overflow" status="todo" scope="quoteFunc" />
    <Check id="19129" location="21147" category="arithmetic.overflow" status="todo" scope="quoteFunc" />
    <Check id="19131" location="21149" category="arithmetic.overflow.warning" status="todo" scope="quoteFunc" />
    <Check id="19132" location="21150" category="arithmetic.overflow" status="todo" scope="quoteFunc" />
    <Check id="19133" location="21151" category="arithmetic.overflow" status="todo" scope="quoteFunc" />
    <Check id="19135" location="21153" category="explicit.conversion.overflow" status="todo" scope="quoteFunc" />
    <Check id="19138" location="21156" category="arithmetic.overflow" status="todo" scope="quoteFunc" />
    <Check id="19139" location="21157" category="arithmetic.overflow" status="todo" scope="quoteFunc" />
    <Check id="19140" location="21158" category="implicit.conversion.overflow" status="todo" scope="quoteFunc" />
    <Check id="19142" location="21160" category="arithmetic.overflow" status="todo" scope="quoteFunc" />
    <Check id="19144" location="21162" category="arithmetic.overflow" status="todo" scope="quoteFunc" />
  </CheckList>
  <Status>initialized</Status>
</VerificationJob>
