<VerificationJob>
  <Configuration>
    <AnalyzeChecksIndividually value="true" />
    <BitcodeTraces value="false" />
    <DumpVerifierBitcodeFiles value="false" />
    <EnableSlicing value="true" />
    <EntryPoint value="btreeCellSizeCheck" />
    <FixPoint value="true" />
    <ForkJobs value="true" />
    <Hosted value="true" />
    <IgnoreMissingFunctions value="false" />
    <InitializedGlobals value="false" />
    <LoopUnrollBound value="1" />
    <PreconditionLocation value="jobs/3299" />
    <PreconditionNumber value="5" />
    <SourceDirectory value="/home/i12/mbuening/100_Dissertation/SQlite/sqlite/bld" />
    <StopEncodingAfterCheck value="true" />
    <StopEncodingAfterCheckLoop value="1" />
    <TimeOut value="600" />
    <XMLTraces value="false" />
  </Configuration>
  <CheckList>
    <Check id="10528" location="11461" category="shift.of.negative" status="safe" scope="btreeCellSizeCheck">
      <EntryStatus>
        <SingleEntryStatus>btreeCellSizeCheck, todo</SingleEntryStatus>
      </EntryStatus>
    </Check>
  </CheckList>
  <Annotation>allsafe</Annotation>
  <Status>allsafe</Status>
</VerificationJob>
