<VerificationJob>
  <Configuration>
    <AnalyzeChecksIndividually value="false" />
    <BitcodeTraces value="false" />
    <DumpVerifierBitcodeFiles value="false" />
    <EnableSlicing value="false" />
    <EntryPoint value="renameEditSql" />
    <FixPoint value="true" />
    <ForkJobs value="true" />
    <Hosted value="true" />
    <IgnoreMissingFunctions value="false" />
    <InitializedGlobals value="false" />
    <LoopUnrollBound value="1" />
    <OverApproxVaArgs value="false" />
    <SourceDirectory value="/home/i12/mbuening/100_Dissertation/SQlite/sqlite/bld" />
    <StopEncodingAfterCheck value="false" />
    <StopEncodingAfterCheckLoop value="0" />
    <TimeOut value="600" />
    <XMLTraces value="false" />
  </Configuration>
  <CheckList>
    <Check id="17226" location="18996" category="arithmetic.overflow" status="todo" scope="renameEditSql" />
    <Check id="17227" location="18997" category="implicit.conversion.overflow" status="todo" scope="renameEditSql" />
    <Check id="17228" location="18997" category="arithmetic.overflow" status="todo" scope="renameEditSql" />
    <Check id="17229" location="18998" category="arithmetic.overflow" status="todo" scope="renameEditSql" />
    <Check id="17230" location="18999" category="arithmetic.overflow" status="todo" scope="renameEditSql" />
    <Check id="17233" location="19002" category="implicit.conversion.overflow" status="todo" scope="renameEditSql" />
    <Check id="17234" location="19002" category="arithmetic.overflow" status="todo" scope="renameEditSql" />
    <Check id="17235" location="19003" category="arithmetic.overflow" status="todo" scope="renameEditSql" />
    <Check id="17236" location="19004" category="arithmetic.overflow" status="todo" scope="renameEditSql" />
    <Check id="17240" location="19008" category="arithmetic.overflow" status="todo" scope="renameEditSql" />
    <Check id="17241" location="19009" category="arithmetic.overflow" status="todo" scope="renameEditSql" />
    <Check id="17244" location="19012" category="arithmetic.overflow" status="todo" scope="renameEditSql" />
    <Check id="17245" location="19013" category="arithmetic.overflow" status="todo" scope="renameEditSql" />
    <Check id="17248" location="19016" category="implicit.conversion.overflow" status="todo" scope="renameEditSql" />
    <Check id="17249" location="19017" category="implicit.conversion.overflow" status="todo" scope="renameEditSql" />
    <Check id="17250" location="19018" category="implicit.conversion.overflow" status="todo" scope="renameEditSql" />
    <Check id="17251" location="19019" category="implicit.conversion.overflow" status="todo" scope="renameEditSql" />
    <Check id="17252" location="19020" category="implicit.conversion.overflow" status="todo" scope="renameEditSql" />
    <Check id="17254" location="19022" category="arithmetic.overflow.warning" status="todo" scope="renameEditSql" />
    <Check id="17257" location="19025" category="implicit.conversion.overflow" status="todo" scope="renameEditSql" />
    <Check id="17258" location="19025" category="arithmetic.overflow" status="todo" scope="renameEditSql" />
    <Check id="17261" location="19028" category="implicit.conversion.overflow" status="todo" scope="renameEditSql" />
    <Check id="17262" location="19029" category="implicit.conversion.overflow" status="todo" scope="renameEditSql" />
    <Check id="17264" location="19030" category="arithmetic.overflow.warning" status="todo" scope="renameEditSql" />
    <Check id="17265" location="19031" category="implicit.conversion.overflow" status="todo" scope="renameEditSql" />
    <Check id="17266" location="19032" category="arithmetic.overflow.warning" status="todo" scope="renameEditSql" />
    <Check id="17267" location="19033" category="implicit.conversion.overflow" status="todo" scope="renameEditSql" />
    <Check id="17269" location="19034" category="arithmetic.overflow.warning" status="todo" scope="renameEditSql" />
    <Check id="17270" location="19035" category="implicit.conversion.overflow" status="todo" scope="renameEditSql" />
    <Check id="17271" location="19036" category="arithmetic.overflow.warning" status="todo" scope="renameEditSql" />
    <Check id="17272" location="19037" category="implicit.conversion.overflow" status="todo" scope="renameEditSql" />
    <Check id="17273" location="19038" category="arithmetic.overflow" status="todo" scope="renameEditSql" />
    <Check id="17274" location="19039" category="arithmetic.overflow.warning" status="todo" scope="renameEditSql" />
  </CheckList>
  <Status>initialized</Status>
</VerificationJob>
