<VerificationJob>
  <Configuration>
    <AnalyzeChecksIndividually value="false" />
    <BitcodeTraces value="false" />
    <DumpVerifierBitcodeFiles value="false" />
    <EnableSlicing value="false" />
    <EntryPoint value="unixSleep" />
    <FixPoint value="true" />
    <ForkJobs value="true" />
    <Hosted value="true" />
    <IgnoreMissingFunctions value="false" />
    <InitializedGlobals value="false" />
    <LoopUnrollBound value="1" />
    <OverApproxVaArgs value="false" />
    <PreconditionLocation value="jobs/1710" />
    <SourceDirectory value="/home/i12/mbuening/100_Dissertation/SQlite/sqlite/bld" />
    <StopEncodingAfterCheck value="false" />
    <StopEncodingAfterCheckLoop value="0" />
    <TimeOut value="600" />
    <XMLTraces value="false" />
  </Configuration>
  <CheckList>
    <Check id="7567" location="8210" category="arithmetic.overflow" status="unsafe|functionbodymissing" scope="unixSleep">
      <Annotations>
        <Annotation>A signed arithmetic operation can overflow.</Annotation>
        <Annotation>The function body for sleep is missing (/home/i12/mbuening/100_Dissertation/SQlite/sqlite/bld//home/i12/mbuening/100_Dissertation/SQlite/sqlite/bld/sqlite3.c:40804:3)</Annotation>
      </Annotations>
    </Check>
    <Check id="7568" location="8211" category="implicit.conversion.overflow" status="unsafe|functionbodymissing" scope="unixSleep">
      <Annotations>
        <Annotation>An implicit conversion operation can overflow.</Annotation>
        <Annotation>The function body for sleep is missing (/home/i12/mbuening/100_Dissertation/SQlite/sqlite/bld//home/i12/mbuening/100_Dissertation/SQlite/sqlite/bld/sqlite3.c:40804:3)</Annotation>
      </Annotations>
    </Check>
    <Check id="7569" location="8212" category="arithmetic.overflow" status="safe|functionbodymissing" scope="unixSleep">
      <Annotations>
        <Annotation>The function body for sleep is missing (/home/i12/mbuening/100_Dissertation/SQlite/sqlite/bld//home/i12/mbuening/100_Dissertation/SQlite/sqlite/bld/sqlite3.c:40804:3)</Annotation>
      </Annotations>
    </Check>
  </CheckList>
  <Annotation>someunsafe</Annotation>
  <Status>someunsafe</Status>
</VerificationJob>
