<VerificationJob>
  <Configuration>
    <AnalyzeChecksIndividually value="false" />
    <BitcodeTraces value="false" />
    <DumpVerifierBitcodeFiles value="false" />
    <EnableSlicing value="false" />
    <EntryPoint value="strftimeFunc" />
    <FixPoint value="true" />
    <ForkJobs value="true" />
    <Hosted value="true" />
    <IgnoreMissingFunctions value="false" />
    <InitializedGlobals value="false" />
    <LoopUnrollBound value="1" />
    <OverApproxVaArgs value="false" />
    <SourceDirectory value="/home/i12/mbuening/100_Dissertation/SQlite/sqlite/bld" />
    <StopEncodingAfterCheck value="false" />
    <StopEncodingAfterCheckLoop value="0" />
    <TimeOut value="600" />
    <XMLTraces value="false" />
  </Configuration>
  <CheckList>
    <Check id="4897" location="5291" category="arithmetic.overflow" status="todo" scope="strftimeFunc" />
    <Check id="4900" location="5294" category="arithmetic.overflow.warning" status="todo" scope="strftimeFunc" />
    <Check id="4901" location="5295" category="arithmetic.overflow.warning" status="todo" scope="strftimeFunc" />
    <Check id="4904" location="5298" category="arithmetic.overflow.warning" status="todo" scope="strftimeFunc" />
    <Check id="4906" location="5300" category="arithmetic.overflow.warning" status="todo" scope="strftimeFunc" />
    <Check id="4907" location="5301" category="arithmetic.overflow.warning" status="todo" scope="strftimeFunc" />
    <Check id="4909" location="5303" category="arithmetic.overflow.warning" status="todo" scope="strftimeFunc" />
    <Check id="4911" location="5305" category="arithmetic.overflow.warning" status="todo" scope="strftimeFunc" />
    <Check id="4913" location="5307" category="arithmetic.overflow.warning" status="todo" scope="strftimeFunc" />
    <Check id="4915" location="5309" category="arithmetic.overflow.warning" status="todo" scope="strftimeFunc" />
    <Check id="4920" location="5313" category="explicit.conversion.overflow" status="todo" scope="strftimeFunc" />
    <Check id="4922" location="5315" category="arithmetic.overflow.warning" status="todo" scope="strftimeFunc" />
    <Check id="4924" location="5317" category="arithmetic.overflow.warning" status="todo" scope="strftimeFunc" />
    <Check id="4925" location="5318" category="arithmetic.overflow.warning" status="todo" scope="strftimeFunc" />
    <Check id="4927" location="5320" category="arithmetic.overflow.warning" status="todo" scope="strftimeFunc" />
    <Check id="4930" location="5323" category="arithmetic.overflow.warning" status="todo" scope="strftimeFunc" />
    <Check id="4932" location="5325" category="arithmetic.overflow.warning" status="todo" scope="strftimeFunc" />
    <Check id="4935" location="5328" category="explicit.conversion.overflow" status="todo" scope="strftimeFunc" />
    <Check id="4938" location="5330" category="arithmetic.overflow" status="todo" scope="strftimeFunc" />
    <Check id="4939" location="5331" category="arithmetic.overflow" status="todo" scope="strftimeFunc" />
    <Check id="4947" location="5338" category="arithmetic.overflow" status="todo" scope="strftimeFunc" />
    <Check id="4953" location="5343" category="arithmetic.overflow" status="todo" scope="strftimeFunc" />
    <Check id="4954" location="5344" category="arithmetic.overflow" status="todo" scope="strftimeFunc" />
    <Check id="4955" location="5345" category="arithmetic.overflow.warning" status="todo" scope="strftimeFunc" />
    <Check id="4957" location="5347" category="arithmetic.overflow" status="todo" scope="strftimeFunc" />
    <Check id="4958" location="5348" category="arithmetic.overflow.warning" status="todo" scope="strftimeFunc" />
    <Check id="4963" location="5352" category="arithmetic.overflow.warning" status="todo" scope="strftimeFunc" />
    <Check id="4965" location="5354" category="arithmetic.overflow.warning" status="todo" scope="strftimeFunc" />
    <Check id="4967" location="5356" category="arithmetic.overflow.warning" status="todo" scope="strftimeFunc" />
    <Check id="4969" location="5358" category="arithmetic.overflow" status="todo" scope="strftimeFunc" />
    <Check id="4976" location="5364" category="arithmetic.overflow.warning" status="todo" scope="strftimeFunc" />
    <Check id="4979" location="5367" category="arithmetic.overflow.warning" status="todo" scope="strftimeFunc" />
    <Check id="4981" location="5369" category="arithmetic.overflow.warning" status="todo" scope="strftimeFunc" />
    <Check id="4982" location="5370" category="implicit.conversion.overflow" status="todo" scope="strftimeFunc" />
    <Check id="4983" location="5370" category="arithmetic.overflow" status="todo" scope="strftimeFunc" />
    <Check id="4989" location="5374" category="arithmetic.overflow" status="todo" scope="strftimeFunc" />
    <Check id="4993" location="5378" category="arithmetic.overflow.warning" status="todo" scope="strftimeFunc" />
    <Check id="4995" location="5380" category="arithmetic.overflow.warning" status="todo" scope="strftimeFunc" />
  </CheckList>
  <Status>initialized</Status>
</VerificationJob>
